build_utils/__init__.py
build_utils/build_context.py
build_utils/docker_utils.py
build_utils/ecr_registry.py
build_utils/execute_build.py
build_utils/execution_context.py
build_utils/input_hash.py
build_utils/local_artifact_store.py
build_utils/local_registry.py
build_utils/s3_artifact_store.py
build_utils/source_utils.py
build_utils/utils.py
build_utils/artifact_store/__init__.py
build_utils/artifact_store/base.py
build_utils/artifact_store/local.py
build_utils/artifact_store/s3.py
build_utils/rules/__init__.py
build_utils/rules/build_docker_image.py
build_utils/rules/build_generic_artifact.py
build_utils/rules/build_maven_artifact.py
build_utils/rules/build_npm_package.py
build_utils/rules/create_elastic_beanstalk_docker_app_bundle.py
build_utils/rules/create_tar_archive.py
build_utils/rules/execute_child_builds.py
build_utils/rules/get_image_tag_from_config.py
build_utils/rules/get_passthrough_config.py
build_utils/rules/write_output_to_cfn_parameters.py
build_utils/rules/write_output_to_hcl.py
build_utils/rules/write_output_to_json.py
vat_build_utils-0.5.4.data/scripts/run_vat_build
vat_build_utils-0.5.4.data/scripts/vat_terraform_init
vat_build_utils-0.5.4.dist-info/LICENSE.txt
vat_build_utils-0.5.4.dist-info/METADATA
vat_build_utils-0.5.4.dist-info/WHEEL
vat_build_utils-0.5.4.dist-info/top_level.txt
vat_build_utils-0.5.4.dist-info/RECORD
